bleakheart/__init__.py
bleakheart/_version.py
bleakheart/core.py
bleakheart-0.1.3.dist-info/LICENSE
bleakheart-0.1.3.dist-info/METADATA
bleakheart-0.1.3.dist-info/WHEEL
bleakheart-0.1.3.dist-info/top_level.txt
bleakheart-0.1.3.dist-info/RECORD
