Metadata-Version: 2.2
Name: bleakheart
Version: 0.1.3
Summary: An asynchronous BLE Heart Monitor library with support for additional data from Polar monitors (ECG, accelerometers, etc)
Author-email: Fabrizio Smeraldi <fabrizio@smeraldi.net>
License: Mozilla Public License Version 2.0
Project-URL: Homepage, https://github.com/fsmeraldi/bleakheart
Project-URL: Repository, https://github.com/fsmeraldi/bleakheart.git
Classifier: Programming Language :: Python :: 3
Classifier: Operating System :: OS Independent
Classifier: License :: OSI Approved :: Mozilla Public License 2.0 (MPL 2.0)
Requires-Python: >=3.10
License-File: LICENSE
Requires-Dist: bleak>=0.21.1
